licensekit/__init__.py
licensekit/cli_issue_license.py
licensekit/cli_make_keys.py
licensekit/cli_make_pyarmor_key.py
licensekit/cli_show_public_key_fingerprint.py
licensekit/context.py
licensekit/crypto.py
licensekit/io.py
licensekit/policy.py
licensekit/runtime.py
licensekit/testing_utils.py
licensekit/token.py
licensekit-0.1.3.dist-info/METADATA
licensekit-0.1.3.dist-info/WHEEL
licensekit-0.1.3.dist-info/entry_points.txt
licensekit-0.1.3.dist-info/licenses/LICENSE
licensekit-0.1.3.dist-info/RECORD
