Metadata-Version: 2.4
Name: licensekit
Version: 0.1.3
Summary: Pure-Python ECDSA license tokens for PyArmor outer keys (bind-data), with plan/feature policy helpers.
License: MIT
License-File: LICENSE
Keywords: license,licensing,pyarmor,obfuscation,ecdsa,feature-flags
Author: Ryan Julyan
Author-email: ryan@julyan.biz
Requires-Python: >=3.9,<4.0
Classifier: Development Status :: 3 - Alpha
Classifier: Intended Audience :: Developers
Classifier: License :: OSI Approved :: MIT License
Classifier: Programming Language :: Python :: 3
Classifier: Programming Language :: Python :: 3.9
Classifier: Programming Language :: Python :: 3.10
Classifier: Programming Language :: Python :: 3.11
Classifier: Programming Language :: Python :: 3.12
Classifier: Programming Language :: Python :: 3.13
Classifier: Programming Language :: Python :: 3.14
Classifier: Topic :: Security :: Cryptography
Classifier: Topic :: Software Development :: Libraries
Provides-Extra: pyarmor
Requires-Dist: ecdsa (>=0.18.0,<0.19.0)
Requires-Dist: pyarmor (>=9.2.3) ; extra == "pyarmor"
Project-URL: Homepage, https://pypi.org/project/licensekit/
Project-URL: Repository, https://github.com/systemizing-solutions/licensekit
